Metadata-Version: 1.1
Name: django-configstore
Version: 0.3
Summary: An application to allow for other apps to easily store site based configurations
Home-page: http://github.com/webcube/django-configstore
Author: Jason Kraus
Author-email: zbyte64@gmail.com
License: BSD
Platform: UNKNOWN
Classifier: Programming Language :: Python
Classifier: Operating System :: OS Independent
Classifier: Natural Language :: English
Classifier: Development Status :: 4 - Beta
Classifier: Intended Audience :: Developers
Classifier: Framework :: Django
Classifier: Topic :: Internet :: WWW/HTTP :: Dynamic Content
